tonprocess/__init__.py
tonprocess/trino_connector.py
tonprocess-0.1.4.dist-info/licenses/LICENSE
tonprocess-0.1.4.dist-info/METADATA
tonprocess-0.1.4.dist-info/WHEEL
tonprocess-0.1.4.dist-info/top_level.txt
tonprocess-0.1.4.dist-info/RECORD
