Metadata-Version: 2.4
Name: tonprocess
Version: 0.1.4
Summary: Secure Trino connector for Python with pandas output
Home-page: https://github.com/kamlesh1114/tonprocess
Author: Kamlesh Kumar
Author-email: kammlesh4@gmail.com
Project-URL: Source, https://github.com/kamlesh1114/pwpy_db
Project-URL: Issues, https://github.com/kamlesh1114/pwpy_db/issues
Keywords: trino presto sql database connector pandas secure encryption
Classifier: Development Status :: 3 - Alpha
Classifier: Intended Audience :: Developers
Classifier: Topic :: Database
Classifier: Topic :: Software Development :: Libraries
Classifier: Programming Language :: Python :: 3
Classifier: Programming Language :: Python :: 3 :: Only
Classifier: License :: OSI Approved :: MIT License
Classifier: Operating System :: OS Independent
Requires-Python: >=3.8
License-File: LICENSE
Requires-Dist: trino>=0.319
Requires-Dist: pandas>=1.0
Requires-Dist: python-dotenv>=1.0
Requires-Dist: psutil>=5.9
Requires-Dist: requests>=2.20
Requires-Dist: cryptography>=41.0
Dynamic: author
Dynamic: author-email
Dynamic: classifier
Dynamic: description-content-type
Dynamic: home-page
Dynamic: keywords
Dynamic: license-file
Dynamic: project-url
Dynamic: requires-dist
Dynamic: requires-python
Dynamic: summary
